easygooglesearch.py
googlesearch.py
easygooglesearch-0.1.0.dist-info/LICENSE
easygooglesearch-0.1.0.dist-info/METADATA
easygooglesearch-0.1.0.dist-info/WHEEL
easygooglesearch-0.1.0.dist-info/top_level.txt
easygooglesearch-0.1.0.dist-info/RECORD
