Metadata-Version: 2.1
Name: easygooglesearch
Version: 0.1.0
Summary: allows access to some Google Search features which may not be easily accessible using the official Google APIs
Home-page: https://github.com/sithsiri/googlesearch.py
Author: sithsiri
License: UNKNOWN
Platform: UNKNOWN
Classifier: Programming Language :: Python :: 3
Classifier: License :: OSI Approved :: GNU General Public License v3 (GPLv3)
Classifier: Operating System :: OS Independent
